tissue/__init__.py
tissue/downstream.py
tissue/experiments.py
tissue/main.py
tissue/utils.py
tissue/SpaGE/__init__.py
tissue/SpaGE/dimensionality_reduction.py
tissue/SpaGE/main.py
tissue/SpaGE/principal_vectors.py
tissue_sc-1.0.1.dist-info/LICENSE
tissue_sc-1.0.1.dist-info/WHEEL
tissue_sc-1.0.1.dist-info/METADATA
tissue_sc-1.0.1.dist-info/RECORD
