Metadata-Version: 2.1
Name: tissue-sc
Version: 1.0.1
Summary: TISSUE (Transcript Imputation with Spatial Single-cell Uncertainty Estimation) provides tools for estimating well-calibrated uncertainty measures for gene expression predictions in single-cell spatial transcriptomics datasets and utilizing them in downstream analyses
Author-email: Eric Sun <edsun97@gmail.com>
Classifier: License :: OSI Approved :: MIT License
Requires-Dist: squidpy>=1.2.3
Project-URL: Home, https://github.com/sunericd/tissue
